lightdl/__init__.py
lightdl/model.py
lightdl-0.0.1.dist-info/LICENSE
lightdl-0.0.1.dist-info/METADATA
lightdl-0.0.1.dist-info/WHEEL
lightdl-0.0.1.dist-info/top_level.txt
lightdl-0.0.1.dist-info/RECORD
