Metadata-Version: 2.1
Name: lightdl
Version: 0.0.1
Summary: LightDL Python Package
Home-page: UNKNOWN
Author: Sichao Yin
Author-email: yinsichao@gmail.com
License: UNKNOWN
Platform: UNKNOWN
Classifier: Programming Language :: Python :: 3
Classifier: License :: OSI Approved :: MIT License
Classifier: Operating System :: OS Independent
Requires-Python: >=3.6
